habr_parser/__init__.py
habr_parser/parser.py
py_habr_parser-1.0.0.dist-info/METADATA
py_habr_parser-1.0.0.dist-info/WHEEL
py_habr_parser-1.0.0.dist-info/top_level.txt
py_habr_parser-1.0.0.dist-info/RECORD
