Metadata-Version: 2.1
Name: py-habr-parser
Version: 1.0.0
Summary: Python library for scraping and retrieving articles, comments, and other content from the Habr website.
Home-page: https://github.com/FlacSy/HabrParser
Author: FlacSy
Author-email: flacsy.x@gmail.com
License: MIT
Keywords: Habr Parser,Habr,Habr API
Platform: UNKNOWN
Classifier: Development Status :: 5 - Production/Stable
Classifier: Intended Audience :: Developers
Classifier: Topic :: Software Development :: Libraries :: Python Modules
Classifier: License :: OSI Approved :: MIT License
Classifier: Programming Language :: Python :: 3
Classifier: Programming Language :: Python :: 3.6
Classifier: Programming Language :: Python :: 3.7
Classifier: Programming Language :: Python :: 3.8
Classifier: Programming Language :: Python :: 3.9
Requires-Dist: requests
Requires-Dist: bs4
